
{"title": "高级前端开发工程师", "work_spot": "深圳", "experience": "3-5年", "edu": "本科", "company": "OPPO ", "salary": "20-35K", "recruiter": "黄女士"},
{"title": "高级后台开发工程师", "work_spot": "深圳", "experience": "经验不限", "edu": "本科", "company": "腾讯互娱 ", "salary": "20-40K·16薪", "recruiter": "莫先生"},
{"title": "大数据开发专家", "work_spot": "杭州", "experience": "5-10年", "edu": "本科", "company": "网易 ", "salary": "45-65K·18薪", "recruiter": "吴女士"},
{"title": "语义分割算法研究员", "work_spot": "杭州", "experience": "5-10年", "edu": "本科", "company": "腾讯 ", "salary": "30-60K", "recruiter": "郑女士"},
{"title": "LAZADA技术专家", "work_spot": "深圳", "experience": "3-5年", "edu": "本科", "company": "阿里巴巴集团 ", "salary": "30-50K", "recruiter": "旷先生"},
{"title": "java工程师(中间件方面)", "work_spot": "上海", "experience": "3-5年", "edu": "本科", "company": "联想集团 ", "salary": "20-35K", "recruiter": "董女士"},
{"title": "高级天线工程师", "work_spot": "深圳", "experience": "5-10年", "edu": "本科", "company": "vivo ", "salary": "30-60K", "recruiter": "陈先生"},
{"title": "Java技术专家", "work_spot": "深圳", "experience": "5-10年", "edu": "本科", "company": "阿里巴巴集团 ", "salary": "30-50K·16薪", "recruiter": "王先生"},
{"title": "推荐算法工程师", "work_spot": "深圳", "experience": "1-3年", "edu": "本科", "company": "vivo ", "salary": "30-60K", "recruiter": "黄先生"},
{"title": "【度小满金融】【百度金融】PHP/C/C++", "work_spot": "北京", "experience": "1-3年", "edu": "本科", "company": "度小满金融 ", "salary": "15-30K", "recruiter": "冯先生"},
{"title": "【度小满金融】【百度金融】C++/C/PHP", "work_spot": "北京", "experience": "1-3年", "edu": "本科", "company": "度小满金融 ", "salary": "15-30K", "recruiter": "冯先生"},
{"title": "金融产品经理 (MJ000643)", "work_spot": "上海", "experience": "3-5年", "edu": "本科", "company": "你我贷 ", "salary": "15-25K", "recruiter": "周女士"},
{"title": "金融产品经理", "work_spot": "烟台", "experience": "1年以内", "edu": "本科", "company": "兴业消费金融 ", "salary": "10-13K", "recruiter": "杨先生"},
{"title": "金融产品总监", "work_spot": "上海", "experience": "3-5年", "edu": "本科", "company": "泽学教育科技金融 ", "salary": "18-25K", "recruiter": "郝女士"},
{"title": "金融产品经理", "work_spot": "昌吉", "experience": "1年以内", "edu": "本科", "company": "宜信普惠金融 ", "salary": "6-10K", "recruiter": "王先生"},
{"title": "产品经理（汽车金融信贷方向）", "work_spot": "深圳", "experience": "5-10年", "edu": "本科", "company": "金服银行科技中心 ", "salary": "15-30K·17薪", "recruiter": "杨女士"},
{"title": "金融产品经理(实习)", "work_spot": "北京", "experience": "经验不限", "edu": "本科", "company": "华信金融 ", "salary": "15-25K", "recruiter": "冯女士"},
{"title": "金融法务", "work_spot": "上海", "experience": "5-10年", "edu": "本科", "company": "快牛金科 ", "salary": "20-30K·17薪", "recruiter": "卞女士"},
{"title": "房地产公司建筑设计师", "work_spot": "青岛", "experience": "3-5年", "edu": "本科", "company": "青岛伟信集团 ", "salary": "8-13K", "recruiter": "高女士"},
{"title": "三维建筑地产、产品、规划影片项目经理/导演", "work_spot": "深圳", "experience": "3-5年", "edu": "大专", "company": "奥视数字视觉 ", "salary": "8-13K", "recruiter": "邓女士"},
{"title": "3D动画设计总监(房地产建筑领域)", "work_spot": "西安", "experience": "3-5年", "edu": "本科", "company": "引力科技西安分公司 ", "salary": "8-10K", "recruiter": "孙女士"},
{"title": "建筑设计经理（房地产开发）", "work_spot": "深圳", "experience": "5-10年", "edu": "本科", "company": "承翰集团 ", "salary": "25-30K", "recruiter": "林先生"},
{"title": "建筑详图", "work_spot": "北京", "experience": "经验不限", "edu": "本科", "company": "筑福集团 ", "salary": "6-11K", "recruiter": "芦女士"},
{"title": "建筑师", "work_spot": "杭州", "experience": "3-5年", "edu": "本科", "company": "基准方中 ", "salary": "15-25K", "recruiter": "贺先生"},
{"title": "建筑电气工程师", "work_spot": "上海", "experience": "5-10年", "edu": "本科", "company": "上海建工总院 ", "salary": "10-15K", "recruiter": "邹先生"},
{"title": "建筑设计师", "work_spot": "晋城", "experience": "5-10年", "edu": "本科", "company": "太行置业 ", "salary": "8-12K", "recruiter": "李女士"},
{"title": "建筑设计师", "work_spot": "济南", "experience": "3-5年", "edu": "本科", "company": "同圆设计 ", "salary": "12-20K", "recruiter": "张先生"},
{"title": "课程顾问/招生顾问/课程销售+教育培训行业", "work_spot": "上海", "experience": "1-3年", "edu": "学历不限", "company": "看看童画 ", "salary": "10-15K", "recruiter": "吴女士"},
{"title": "其他教育培训职位", "work_spot": "昆明", "experience": "1-3年", "edu": "大专", "company": "行动教育 ", "salary": "30-50K", "recruiter": "包女士"},
{"title": "品牌文案策划(教育培训行业）", "work_spot": "上海", "experience": "1年以内", "edu": "大专", "company": "昂立教育 ", "salary": "6-8K", "recruiter": "范女士"},
{"title": "产品总监（AI教育培训方向）", "work_spot": "北京", "experience": "5-10年", "edu": "硕士", "company": "中科神探 ", "salary": "20-40K", "recruiter": "袁先生"},
{"title": "教育培训指导讲师", "work_spot": "福州", "experience": "3-5年", "edu": "大专", "company": "为学托辅教育 ", "salary": "5-8K", "recruiter": "李女士"},
{"title": "教育培训班主任", "work_spot": "北京", "experience": "1-3年", "edu": "本科", "company": "校内外 ", "salary": "6-10K", "recruiter": "吕女士"},
{"title": "教育培训/招生/课程顾问", "work_spot": "上海", "experience": "1年以内", "edu": "本科", "company": "金宝贝 ", "salary": "10-15K", "recruiter": "王女士"},
{"title": "学历教育培训事业部经理", "work_spot": "贵阳", "experience": "1-3年", "edu": "大专", "company": "高鹏集团 ", "salary": "5-8K", "recruiter": "赵女士"},
{"title": "教育培训主管", "work_spot": "南京", "experience": "1-3年", "edu": "本科", "company": "常青藤教育 ", "salary": "6-9K", "recruiter": "张先生"},
{"title": "汽车售后系统产品经理", "work_spot": "北京", "experience": "3-5年", "edu": "大专", "company": "中恒天 ", "salary": "15-20K", "recruiter": "HR"},
{"title": "汽车", "work_spot": "佛山", "experience": "经验不限", "edu": "中专/中技", "company": "喜相逢汽车 ", "salary": "5-8K", "recruiter": "林女士"},
{"title": "汽车销售", "work_spot": "石家庄", "experience": "经验不限", "edu": "高中", "company": "山西喜相逢 ", "salary": "5-9K", "recruiter": "赵女士"},
{"title": "汽车销售", "work_spot": "太原", "experience": "经验不限", "edu": "高中", "company": "山西喜相逢 ", "salary": "5-10K", "recruiter": "赵女士"},
{"title": "汽车销售顾问", "work_spot": "沈阳", "experience": "1-3年", "edu": "大专", "company": "花生好车 ", "salary": "5-10K", "recruiter": "张先生"},
{"title": "售前咨询-汽车智能网联", "work_spot": "沈阳", "experience": "5-10年", "edu": "本科", "company": "东软睿驰 ", "salary": "10-15K", "recruiter": "HR"},
{"title": "汽车代表", "work_spot": "深圳", "experience": "经验不限", "edu": "学历不限", "company": "有道 ", "salary": "9-10K", "recruiter": "潘女士"},
{"title": "汽车销售", "work_spot": "佛山", "experience": "经验不限", "edu": "高中", "company": "山西喜相逢 ", "salary": "6-10K", "recruiter": "赵女士"},
{"title": "汽车电子工程师", "work_spot": "深圳", "experience": "1-3年", "edu": "大专", "company": "赛森汽车电子 ", "salary": "10-15K", "recruiter": "黄女士"},
{"title": "传媒经纪人", "work_spot": "长春", "experience": "1年以内", "edu": "本科", "company": "泽诚科技 ", "salary": "6-8K", "recruiter": "宋女士"},
{"title": "传媒销售", "work_spot": "济南", "experience": "1年以内", "edu": "大专", "company": "山东启信文化传媒 ", "salary": "6-8K", "recruiter": "闫女士"},
{"title": "传媒经纪人", "work_spot": "深圳", "experience": "1年以内", "edu": "大专", "company": "世纪博湾 ", "salary": "8-13K", "recruiter": "唐女士"},
{"title": "传媒经理", "work_spot": "上海", "experience": "3-5年", "edu": "本科", "company": "东匠传媒 ", "salary": "10-15K", "recruiter": "宋女士"},
{"title": "传媒设计师", "work_spot": "长春", "experience": "3-5年", "edu": "本科", "company": "三合弘业 ", "salary": "6-8K", "recruiter": "任女士"},
{"title": "传媒老师", "work_spot": "郑州", "experience": "1-3年", "edu": "本科", "company": "天籁教育 ", "salary": "8-12K", "recruiter": "薛女士"},
{"title": "传媒销售", "work_spot": "济南", "experience": "经验不限", "edu": "学历不限", "company": "启信传媒 ", "salary": "6-8K", "recruiter": "顾女士"},
{"title": "传媒销售", "work_spot": "合肥", "experience": "经验不限", "edu": "中专/中技", "company": "信达天下 ", "salary": "7-12K", "recruiter": "王女士"},
{"title": "市场传媒经理", "work_spot": "天津", "experience": "3-5年", "edu": "本科", "company": "融侨置业酒店分公司 ", "salary": "7-8K", "recruiter": "郭女士"},
{"title": "医疗健康APP产品运营专家", "work_spot": "北京", "experience": "5-10年", "edu": "本科", "company": "BOE ", "salary": "15-30K", "recruiter": "招聘经理"},
{"title": "医疗健康产品经理", "work_spot": "杭州", "experience": "1-3年", "edu": "硕士", "company": "健驰医疗 ", "salary": "10-15K", "recruiter": "吕先生"},
{"title": "医疗健康项目经理", "work_spot": "杭州", "experience": "1-3年", "edu": "硕士", "company": "健驰医疗 ", "salary": "10-15K", "recruiter": "吕先生"},
{"title": "产品经理（医疗健康）", "work_spot": "北京", "experience": "1-3年", "edu": "本科", "company": "南瑞 ", "salary": "15-20K", "recruiter": "陆先生"},
{"title": "医疗健康顾问", "work_spot": "南京", "experience": "1年以内", "edu": "学历不限", "company": "南京邦德骨科医院 ", "salary": "8-16K", "recruiter": "潘女士"},
{"title": "医疗健康管理经理", "work_spot": "深圳", "experience": "3-5年", "edu": "大专", "company": "精医科技 ", "salary": "10-15K·13薪", "recruiter": "肖先生"},
{"title": "记者（医疗健康方向）", "work_spot": "北京", "experience": "1-3年", "edu": "本科", "company": "猎云网 ", "salary": "8-16K", "recruiter": "姚先生"},
{"title": "医疗健康器械店长", "work_spot": "广州", "experience": "经验不限", "edu": "高中", "company": "盛世东泰 ", "salary": "6-10K", "recruiter": "谢女士"},
{"title": "医疗健康器械店长", "work_spot": "深圳", "experience": "经验不限", "edu": "学历不限", "company": "盛世东泰 ", "salary": "5-10K", "recruiter": "袁女士"},
{"title": "课程顾问", "work_spot": "北京", "experience": "经验不限", "edu": "大专", "company": "英孚教育 ", "salary": "20-40K", "recruiter": "王女士"},
{"title": "翻译算法专家", "work_spot": "杭州", "experience": "3-5年", "edu": "硕士", "company": "阿里巴巴集团 ", "salary": "30-60K", "recruiter": "赵先生"},
{"title": "翻译", "work_spot": "深圳", "experience": "1-3年", "edu": "大专", "company": "三态股份 ", "salary": "5-10K", "recruiter": "王先生"},
{"title": "印尼语翻译", "work_spot": "北京", "experience": "1年以内", "edu": "本科", "company": "RADIO ", "salary": "10-15K", "recruiter": "刘先生"},
{"title": "法语翻译", "work_spot": "北京", "experience": "经验不限", "edu": "本科", "company": "四达时代 ", "salary": "7-12K", "recruiter": "辛女士"},
{"title": "英语翻译", "work_spot": "深圳", "experience": "应届生", "edu": "大专", "company": "腾讯 ", "salary": "6-9K", "recruiter": "蔡女士"},
{"title": "通信翻译", "work_spot": "日照", "experience": "经验不限", "edu": "本科", "company": "RWS中国 ", "salary": "5-8K", "recruiter": "李先生"},
{"title": "搜狗机器翻译-产品经理", "work_spot": "北京", "experience": "3-5年", "edu": "本科", "company": "搜狗 ", "salary": "20-30K", "recruiter": "卢先生"},
{"title": "日语翻译(兼职)", "work_spot": "南京", "experience": "经验不限", "edu": "学历不限", "company": "汉资餐饮 ", "salary": "10-15K", "recruiter": "朱女士"},
{"title": "研发经理（金融/物流/供应链/会员/中后台）", "work_spot": "南京", "experience": "5-10年", "edu": "本科", "company": "孩子王 ", "salary": "20-40K", "recruiter": "李女士"},
{"title": "助理实施顾问（物流、供应链、生产制造方向）", "work_spot": "深圳", "experience": "应届生", "edu": "本科", "company": "鼎捷软件 ", "salary": "5-7K", "recruiter": "曾女士"},
{"title": "后台产品经理（仓储、物流、供应链方向）", "work_spot": "北京", "experience": "3-5年", "edu": "大专", "company": "OFashion ", "salary": "18-30K", "recruiter": "邹女士"},
{"title": "技术总监（金融/物流/供应链/会员/中后台）", "work_spot": "南京", "experience": "5-10年", "edu": "本科", "company": "孩子王 ", "salary": "20-40K", "recruiter": "李女士"},
{"title": "助理实施顾问（生产制造/物流/供应链等模块）", "work_spot": "东莞", "experience": "应届生", "edu": "本科", "company": "鼎捷软件 ", "salary": "6-7K", "recruiter": "曾女士"},
{"title": "供应链物流主管", "work_spot": "东莞", "experience": "经验不限", "edu": "学历不限", "company": "美菜网 ", "salary": "5-8K·13薪", "recruiter": "李先生"},
{"title": "盒马供应链物流产品经理/专家", "work_spot": "上海", "experience": "5-10年", "edu": "本科", "company": "盒马生鲜 ", "salary": "20-40K", "recruiter": "顾先生"},
{"title": "海外市场专员（仓储物流供应链）", "work_spot": "广州", "experience": "经验不限", "edu": "本科", "company": "SHEIN ", "salary": "6-10K", "recruiter": "刘先生"},
{"title": "供应链物流专员", "work_spot": "深圳", "experience": "经验不限", "edu": "大专", "company": "雷特科技 ", "salary": "5-8K", "recruiter": "戴女士"},
{"title": "国际贸易跟单", "work_spot": "上海", "experience": "1年以内", "edu": "本科", "company": "佳农食品控股（集... ", "salary": "5-7K", "recruiter": "戴女士"},
{"title": "国际贸易", "work_spot": "上海", "experience": "1-3年", "edu": "本科", "company": "垚森 ", "salary": "10-11K", "recruiter": "姜女士"},
{"title": "采购经理（一般贸易）", "work_spot": "杭州", "experience": "3-5年", "edu": "大专", "company": "海带 ", "salary": "15-25K·13薪", "recruiter": "吴女士"},
{"title": "采购贸易专员", "work_spot": "重庆", "experience": "经验不限", "edu": "大专", "company": "和讯 ", "salary": "5-10K", "recruiter": "周女士"},
{"title": "阿里巴巴国际站授权渠道贸易专员", "work_spot": "潍坊", "experience": "经验不限", "edu": "大专", "company": "龙升绘宏 ", "salary": "5-10K", "recruiter": "刘女士"},
{"title": "贸易文员", "work_spot": "北京", "experience": "1年以内", "edu": "本科", "company": "德格乐家 ", "salary": "5-10K", "recruiter": "王女士"},
{"title": "贸易跟单", "work_spot": "深圳", "experience": "1-3年", "edu": "本科", "company": "生活构造 ", "salary": "5-7K", "recruiter": "徐先生"},
{"title": "采购专员/跨境贸易", "work_spot": "北京", "experience": "1-3年", "edu": "大专", "company": "爱恩刻 ", "salary": "6-10K", "recruiter": "王女士"},
{"title": "贸易跟单", "work_spot": "深圳", "experience": "1年以内", "edu": "大专", "company": "力诚 ", "salary": "5-8K", "recruiter": "张女士"}

